jsoneditor.py
jsoneditor-0.2.0.dist-info/METADATA
jsoneditor-0.2.0.dist-info/WHEEL
jsoneditor-0.2.0.dist-info/top_level.txt
jsoneditor-0.2.0.dist-info/RECORD
