Metadata-Version: 2.1
Name: jsoneditor
Version: 0.2.0
Summary: Visualize and edit JSON
Home-page: https://github.com/dermasmid/py-jsoneditor
Author: Cheskel Twersky
Author-email: twerskycheskel@gmail.com
License: MIT
Keywords: python3 JSON jsoneditor
Platform: UNKNOWN
Classifier: Programming Language :: Python :: 3
Classifier: License :: OSI Approved :: MIT License
Classifier: Operating System :: OS Independent
Requires-Python: >=3.6
Requires-Dist: flask
